.DS_Store
pysandboxing/__init__.py
pysandboxing/sandbox.py
pysandboxing-0.1.4.dist-info/METADATA
pysandboxing-0.1.4.dist-info/WHEEL
pysandboxing-0.1.4.dist-info/top_level.txt
pysandboxing-0.1.4.dist-info/RECORD
