Metadata-Version: 2.2
Name: pysandboxing
Version: 0.1.4
Summary: A Python module for sandboxing code with restricted imports and timeout enforcement (Linux/macOS only)
Home-page: https://github.com/libardoram/pysandboxing
Author: Libardo Ramirez Tirado
Author-email: libar@libardoramirez.com
Keywords: sandboxing security
Classifier: Programming Language :: Python :: 3
Classifier: License :: OSI Approved :: MIT License
Classifier: Operating System :: POSIX :: Linux
Classifier: Operating System :: MacOS
Requires-Python: >=3.6
Dynamic: author
Dynamic: author-email
Dynamic: classifier
Dynamic: description
Dynamic: description-content-type
Dynamic: home-page
Dynamic: keywords
Dynamic: requires-python
Dynamic: summary
